my_tool.py
irlpdf/__init__.py
irlpdf/__main__.py
irlpdf/cli.py
irlpdf/commands/__init__.py
irlpdf/commands/compress.py
irlpdf/commands/decrypt.py
irlpdf/commands/encrypt.py
irlpdf/commands/man.py
irlpdf/commands/merge.py
irlpdf/commands/rmpg.py
irlpdf/commands/split.py
irlpdf/commands/stats.py
irlpdf-0.1.8.dist-info/licenses/LICENSE
irlpdf-0.1.8.dist-info/METADATA
irlpdf-0.1.8.dist-info/WHEEL
irlpdf-0.1.8.dist-info/entry_points.txt
irlpdf-0.1.8.dist-info/top_level.txt
irlpdf-0.1.8.dist-info/RECORD
