Metadata-Version: 2.4
Name: irlpdf
Version: 0.1.8
Summary: CLI tool for pdf related tasks
Home-page: https://github.com/dusa-sai-krishna/irlpdf
Author: Gauraang Ratnaparik
Author-email: john.doe@foo.com
License: MIT
Classifier: Programming Language :: Python :: 3.8
Classifier: Operating System :: OS Independent
Requires-Python: >=3.9
License-File: LICENSE
Requires-Dist: typer==0.12.4
Requires-Dist: pypdf2==3.0.1
Dynamic: author
Dynamic: author-email
Dynamic: classifier
Dynamic: description
Dynamic: description-content-type
Dynamic: home-page
Dynamic: license
Dynamic: license-file
Dynamic: requires-dist
Dynamic: requires-python
Dynamic: summary
